ShejiShujuMijixingYingyongChufan/README.md
ShejiShujuMijixingYingyongChufan/__init__.py
ShejiShujuMijixingYingyongChufan/__main__.py
ShejiShujuMijixingYingyongChufan/file.epub
ShejiShujuMijixingYingyongChufan/index.html
ShejiShujuMijixingYingyongChufan/css/__init__.py
ShejiShujuMijixingYingyongChufan/css/annotations.css
ShejiShujuMijixingYingyongChufan/css/main.css
ShejiShujuMijixingYingyongChufan/css/normalize.css
ShejiShujuMijixingYingyongChufan/css/popup.css
ShejiShujuMijixingYingyongChufan/font/__init__.py
ShejiShujuMijixingYingyongChufan/font/fontello.eot
ShejiShujuMijixingYingyongChufan/font/fontello.svg
ShejiShujuMijixingYingyongChufan/font/fontello.ttf
ShejiShujuMijixingYingyongChufan/font/fontello.woff
ShejiShujuMijixingYingyongChufan/img/__init__.py
ShejiShujuMijixingYingyongChufan/img/annotator-glyph-sprite.png
ShejiShujuMijixingYingyongChufan/img/annotator-icon-sprite.png
ShejiShujuMijixingYingyongChufan/img/apple-touch-icon.png
ShejiShujuMijixingYingyongChufan/img/cancelfullscreen.png
ShejiShujuMijixingYingyongChufan/img/close.png
ShejiShujuMijixingYingyongChufan/img/fullscreen.png
ShejiShujuMijixingYingyongChufan/img/loader.gif
ShejiShujuMijixingYingyongChufan/img/menu-icon.png
ShejiShujuMijixingYingyongChufan/img/save.png
ShejiShujuMijixingYingyongChufan/img/saved.png
ShejiShujuMijixingYingyongChufan/img/settings-s.png
ShejiShujuMijixingYingyongChufan/img/settings.png
ShejiShujuMijixingYingyongChufan/img/star.png
ShejiShujuMijixingYingyongChufan/js/__init__.py
ShejiShujuMijixingYingyongChufan/js/epub.js
ShejiShujuMijixingYingyongChufan/js/epub.min.js
ShejiShujuMijixingYingyongChufan/js/epub.min.map
ShejiShujuMijixingYingyongChufan/js/hooks.min.js
ShejiShujuMijixingYingyongChufan/js/hooks.min.map
ShejiShujuMijixingYingyongChufan/js/reader.js
ShejiShujuMijixingYingyongChufan/js/reader.js.map
ShejiShujuMijixingYingyongChufan/js/reader.min.js
ShejiShujuMijixingYingyongChufan/js/reader.min.map
ShejiShujuMijixingYingyongChufan/js/hooks/__init__.py
sheji_shuju_mijixing_yingyong_chufan-2024.3.3.0.dist-info/METADATA
sheji_shuju_mijixing_yingyong_chufan-2024.3.3.0.dist-info/WHEEL
sheji_shuju_mijixing_yingyong_chufan-2024.3.3.0.dist-info/entry_points.txt
sheji_shuju_mijixing_yingyong_chufan-2024.3.3.0.dist-info/top_level.txt
sheji_shuju_mijixing_yingyong_chufan-2024.3.3.0.dist-info/RECORD
